easysim/__init__.py
easysim/body.py
easysim/camera.py
easysim/cmd.py
easysim/config.py
easysim/constants.py
easysim/contact.py
easysim/py.typed
easysim/scene.py
easysim/simulator_env.py
easysim/simulators/bullet.py
easysim/simulators/isaac_gym.py
easysim/simulators/registration.py
easysim/simulators/simulator.py
easysim-1.2.0.dist-info/LICENSE
easysim-1.2.0.dist-info/METADATA
easysim-1.2.0.dist-info/WHEEL
easysim-1.2.0.dist-info/top_level.txt
easysim-1.2.0.dist-info/RECORD
