Metadata-Version: 2.1
Name: easysim
Version: 1.2.0
Summary: A library for creating Gym environments with unified API to various physics simulators
Home-page: https://github.com/NVlabs/easysim
Author: Yu-Wei Chao
License: MIT
Platform: any
Classifier: Intended Audience :: Developers
Classifier: License :: OSI Approved :: MIT License
Classifier: Natural Language :: English
Classifier: Operating System :: OS Independent
Classifier: Programming Language :: Python :: 3
Classifier: Topic :: Scientific/Engineering
License-File: LICENSE
Requires-Dist: gym
Requires-Dist: numpy
Requires-Dist: pybullet
Requires-Dist: setuptools-scm
Requires-Dist: torch
Requires-Dist: yacs
Provides-Extra: dev
Requires-Dist: anybadge (==1.8.0) ; extra == 'dev'
Requires-Dist: black (==21.12b0) ; extra == 'dev'
Requires-Dist: build (==0.7.0) ; extra == 'dev'
Requires-Dist: graphviz (==0.19.1) ; extra == 'dev'
Requires-Dist: flake8 (==4.0.1) ; extra == 'dev'
Requires-Dist: flake8-copyright (==0.2.2) ; extra == 'dev'
Requires-Dist: flake8-docstrings (==1.6.0) ; extra == 'dev'
Requires-Dist: flake8-isort (==4.1.1) ; extra == 'dev'
Requires-Dist: mypy (==0.931) ; extra == 'dev'
Requires-Dist: pytest (==6.2.5) ; extra == 'dev'
Requires-Dist: pytest-cov (==3.0.0) ; extra == 'dev'
Requires-Dist: sphinx (==4.3.0) ; extra == 'dev'
Requires-Dist: sphinx-rtd-theme (==1.0.0) ; extra == 'dev'
Requires-Dist: twine (==3.7.1) ; extra == 'dev'
